base_folder/__init__.py
base_folder/browser.py
base_folder/definition.py
base_folder/locators.py
hellosmalldemo/__init__.py
hellosmalldemo/hello.py
vidstream/__init__.py
vidstream/audio.py
vidstream/streaming.py
vidstreamtestdemo/__init__.py
vidstreamtestdemo/audio.py
vidstreamtestdemo/streaming.py
hellosmalldemo-0.0.1.dist-info/LICENSE
hellosmalldemo-0.0.1.dist-info/METADATA
hellosmalldemo-0.0.1.dist-info/WHEEL
hellosmalldemo-0.0.1.dist-info/top_level.txt
hellosmalldemo-0.0.1.dist-info/RECORD
